{
  "plan_name": "UTA100 Race Plan V1",
  "gpx_filename": "UTA100.gpx",
  "checkpoint_distances": [
    13.7,
    23.7,
    37.7,
    51.6,
    68.5,
    79.6
  ],
  "avg_cp_time": 10,
  "z2_pace": 5.5,
  "elev_gain_factor": 6,
  "carbs_per_hour": 60,
  "water_per_hour": 500,
  "race_start_time": null,
  "segments": [
    {
      "cumulative_time": 100.44,
      "cumulative_time_str": "01:40:26",
      "distance": 13.7,
      "elev_gain": 367,
      "elev_loss": 387,
      "elev_pace": 7.33,
      "elev_pace_str": "7:19",
      "fatigue_seconds": 0,
      "fatigue_str": "+0:00",
      "from": "Start",
      "net_elev": -21,
      "pace": 7.33,
      "pace_str": "7:19",
      "segment_time": 100.44,
      "segment_time_str": "01:40:26",
      "target_carbs": 100,
      "target_water": 0.8,
      "time_of_day": null,
      "to": "CP1"
    },
    {
      "cumulative_time": 174.01,
      "cumulative_time_str": "02:54:00",
      "distance": 9.99,
      "elev_gain": 228,
      "elev_loss": 543,
      "elev_pace": 6.15,
      "elev_pace_str": "6:09",
      "fatigue_seconds": 12.4,
      "fatigue_str": "+0:12",
      "from": "CP1",
      "net_elev": -314,
      "pace": 6.36,
      "pace_str": "6:21",
      "segment_time": 63.57,
      "segment_time_str": "01:03:34",
      "target_carbs": 60,
      "target_water": 0.5,
      "time_of_day": null,
      "to": "CP2"
    },
    {
      "cumulative_time": 298.34,
      "cumulative_time_str": "04:58:20",
      "distance": 14.01,
      "elev_gain": 474,
      "elev_loss": 535,
      "elev_pace": 7.74,
      "elev_pace_str": "7:44",
      "fatigue_seconds": 25.4,
      "fatigue_str": "+0:25",
      "from": "CP2",
      "net_elev": -61,
      "pace": 8.16,
      "pace_str": "8:09",
      "segment_time": 114.33,
      "segment_time_str": "01:54:19",
      "target_carbs": 110,
      "target_water": 1,
      "time_of_day": null,
      "to": "CP3"
    },
    {
      "cumulative_time": 431.82,
      "cumulative_time_str": "07:11:49",
      "distance": 13.9,
      "elev_gain": 446,
      "elev_loss": 268,
      "elev_pace": 8.13,
      "elev_pace_str": "8:07",
      "fatigue_seconds": 45.2,
      "fatigue_str": "+0:45",
      "from": "CP3",
      "net_elev": 178,
      "pace": 8.88,
      "pace_str": "8:52",
      "segment_time": 123.48,
      "segment_time_str": "02:03:28",
      "target_carbs": 120,
      "target_water": 1,
      "time_of_day": null,
      "to": "CP4"
    },
    {
      "cumulative_time": 605.14,
      "cumulative_time_str": "10:05:08",
      "distance": 16.9,
      "elev_gain": 670,
      "elev_loss": 533,
      "elev_pace": 8.52,
      "elev_pace_str": "8:31",
      "fatigue_seconds": 68.5,
      "fatigue_str": "+1:08",
      "from": "CP4",
      "net_elev": 137,
      "pace": 9.66,
      "pace_str": "9:39",
      "segment_time": 163.32,
      "segment_time_str": "02:43:19",
      "target_carbs": 160,
      "target_water": 1.4,
      "time_of_day": null,
      "to": "CP5"
    },
    {
      "cumulative_time": 704.81,
      "cumulative_time_str": "11:44:48",
      "distance": 11.09,
      "elev_gain": 242,
      "elev_loss": 325,
      "elev_pace": 6.8,
      "elev_pace_str": "6:48",
      "fatigue_seconds": 76.9,
      "fatigue_str": "+1:16",
      "from": "CP5",
      "net_elev": -83,
      "pace": 8.09,
      "pace_str": "8:05",
      "segment_time": 89.66,
      "segment_time_str": "01:29:39",
      "target_carbs": 90,
      "target_water": 0.7,
      "time_of_day": null,
      "to": "CP6"
    },
    {
      "cumulative_time": 941.65,
      "cumulative_time_str": "15:41:38",
      "distance": 20.62,
      "elev_gain": 1114,
      "elev_loss": 951,
      "elev_pace": 9.52,
      "elev_pace_str": "9:31",
      "fatigue_seconds": 124.7,
      "fatigue_str": "+2:04",
      "from": "CP6",
      "net_elev": 163,
      "pace": 11,
      "pace_str": "11:00",
      "segment_time": 226.84,
      "segment_time_str": "03:46:50",
      "target_carbs": 230,
      "target_water": 1.9,
      "time_of_day": null,
      "to": "Finish"
    }
  ],
  "summary": {
    "total_carbs": 870,
    "total_cp_time": 60,
    "total_cp_time_str": "01:00:00",
    "total_distance": 100.22,
    "total_elev_gain": 3541,
    "total_moving_time": 881.65,
    "total_moving_time_str": "14:41:38",
    "total_race_time": 941.65,
    "total_race_time_str": "15:41:38",
    "total_water": 7.3
  }
}